{
    "compressionlevel": -1,
    "height": 11,
    "infinite": false,
    "layers": [
        {
            "data": [
                0, 0, 0, 0, 0, 0, 0, 0, 0, 0, 0, 0, 0, 0, 0, 0, 0, 0, 0, 0, 0,
                0, 0, 0, 0, 0, 0, 0, 0, 0, 0, 0, 0, 0, 0, 0, 0, 0, 0, 0, 0, 0,
                0, 0, 0, 0, 0, 0, 0, 0, 0, 1, 2, 2, 0, 0, 0, 0, 0, 0, 0, 0, 0,
                0, 0, 0, 11, 12, 12, 0, 0, 0, 0, 0, 0, 0, 0, 0, 0, 0, 0, 11, 12,
                12, 0, 0, 0, 0, 0, 0, 0, 0, 0, 0, 0, 0, 11, 12, 12, 2, 0, 0, 0,
                0, 0, 0, 0, 0, 0, 0, 0, 11, 12, 12, 12, 2, 0, 0, 0, 0, 0, 2, 2,
                2, 2, 2, 26, 12, 12, 0, 0, 0, 0, 0, 0, 0, 0, 0, 0, 0, 0, 0, 0,
                0, 0, 0, 0, 0, 0, 0, 0, 0, 0, 0, 0, 0, 0, 0, 0, 0, 0, 2, 2, 2, 0
            ],
            "height": 11,
            "id": 1,
            "name": "Tile_Layer_1",
            "opacity": 1,
            "type": "tilelayer",
            "visible": true,
            "width": 15,
            "x": 0,
            "y": 0
        },
        {
            "draworder": "topdown",
            "id": 5,
            "name": "Object_Layer_1",
            "objects": [
                {
                    "height": 0,
                    "id": 6,
                    "name": "coin",
                    "opacity": 1,
                    "rotation": 0,
                    "type": "",
                    "visible": true,
                    "width": 0,
                    "x": 271.662206363366,
                    "y": 79.92863514719
                },
                {
                    "height": 0,
                    "id": 7,
                    "name": "coin",
                    "opacity": 1,
                    "rotation": 0,
                    "type": "",
                    "visible": true,
                    "width": 0,
                    "x": 239.78590544157,
                    "y": 79.4528694617901
                },
                {
                    "height": 0,
                    "id": 8,
                    "name": "coin",
                    "opacity": 1,
                    "rotation": 0,
                    "type": "",
                    "visible": true,
                    "width": 0,
                    "x": 143.681236990782,
                    "y": 240.26167112697
                },
                {
                    "height": 0,
                    "id": 9,
                    "name": "coin",
                    "opacity": 1,
                    "rotation": 0,
                    "type": "",
                    "visible": true,
                    "width": 0,
                    "x": 111.329170383586,
                    "y": 240.73743681237
                },
                {
                    "height": 0,
                    "id": 10,
                    "name": "coin",
                    "opacity": 1,
                    "rotation": 0,
                    "type": "",
                    "visible": true,
                    "width": 0,
                    "x": 79.45286946179,
                    "y": 240.26167112697
                }
            ],
            "opacity": 1,
            "type": "objectgroup",
            "visible": true,
            "x": 0,
            "y": 0
        },
        {
            "data": [
                0, 0, 0, 0, 0, 0, 0, 0, 0, 0, 0, 0, 0, 0, 0, 0, 0, 0, 0, 0, 0,
                0, 0, 0, 0, 0, 0, 0, 0, 0, 0, 0, 0, 0, 0, 0, 0, 0, 0, 0, 0, 0,
                0, 0, 0, 0, 0, 0, 0, 0, 0, 15, 15, 15, 0, 0, 0, 0, 0, 0, 0, 0,
                0, 0, 0, 0, 15, 15, 15, 0, 0, 0, 0, 0, 0, 0, 0, 0, 0, 0, 0, 15,
                15, 15, 0, 0, 0, 0, 0, 0, 0, 0, 0, 0, 0, 0, 15, 15, 15, 15, 0,
                0, 0, 0, 0, 0, 0, 0, 0, 0, 0, 15, 15, 15, 15, 15, 0, 0, 0, 0, 0,
                15, 15, 15, 15, 15, 15, 15, 15, 0, 0, 0, 0, 0, 0, 0, 0, 0, 0, 0,
                0, 0, 0, 0, 0, 0, 0, 0, 0, 0, 0, 0, 0, 0, 0, 0, 0, 0, 0, 0, 0,
                15, 15, 15, 0
            ],
            "height": 11,
            "id": 2,
            "name": "Collision_Layer",
            "opacity": 1,
            "type": "tilelayer",
            "visible": true,
            "width": 15,
            "x": 0,
            "y": 0
        }
    ],
    "nextlayerid": 6,
    "nextobjectid": 11,
    "orientation": "orthogonal",
    "renderorder": "right-down",
    "tiledversion": "1.12.1",
    "tileheight": 32,
    "tilesets": [
        {
            "firstgid": 1,
            "source": "tileset4_ice.tsx"
        }
    ],
    "tilewidth": 32,
    "type": "map",
    "version": "1.10",
    "width": 15
}
